neo_api_client/HSWebSocketLib.py
neo_api_client/NeoWebSocket.py
neo_api_client/__init__.py
neo_api_client/api_client.py
neo_api_client/demo.py
neo_api_client/exceptions.py
neo_api_client/neo_api.py
neo_api_client/neo_utility.py
neo_api_client/req_data_validation.py
neo_api_client/rest.py
neo_api_client/settings.py
neo_api_client/urls.py
neo_api_client/api/__init__.py
neo_api_client/api/limits_api.py
neo_api_client/api/login_api.py
neo_api_client/api/logout_api.py
neo_api_client/api/margin_api.py
neo_api_client/api/modify_order_api.py
neo_api_client/api/order_api.py
neo_api_client/api/order_history_api.py
neo_api_client/api/order_report_api.py
neo_api_client/api/portfolio_holdings_api.py
neo_api_client/api/positions_api.py
neo_api_client/api/scrip_master_api.py
neo_api_client/api/scrip_search.py
neo_api_client/api/trade_report_api.py
pk_neo_api_client-1.0.3.dist-info/METADATA
pk_neo_api_client-1.0.3.dist-info/WHEEL
pk_neo_api_client-1.0.3.dist-info/top_level.txt
pk_neo_api_client-1.0.3.dist-info/RECORD
