Metadata-Version: 2.1
Name: pk-neo-api-client
Version: 1.0.3
Summary: Neo Trade API
Home-page: UNKNOWN
Author: ne API
Author-email: 
License: UNKNOWN
Keywords: Neo-Trade API,Neo Trade API's
Platform: UNKNOWN
Requires-Dist: bidict ==0.22.1
Requires-Dist: certifi ==2022.12.7
Requires-Dist: idna ==2.10
Requires-Dist: numpy ==1.24.2
Requires-Dist: pyjsparser ==2.7.1
Requires-Dist: PyJWT ==2.6.0
Requires-Dist: python-dateutil ==2.8.2
Requires-Dist: python-dotenv ==1.0.0
Requires-Dist: requests ==2.25.1
Requires-Dist: six ==1.16.0
Requires-Dist: urllib3 ==1.26.14
Requires-Dist: websocket-client ==1.5.1
Requires-Dist: websockets ==8.1
Requires-Dist: pandas ==2.0.0
Requires-Dist: asyncio ==3.4.3
